CHANGES.txt
CONTRIBUTORS.txt
EXTERNALS.txt
README.txt
bootstrap.py
buildout.cfg
sample.cfg
setup.py
zeo.cfg
collective/__init__.py
collective.recipe.zope2wsgi.egg-info/PKG-INFO
collective.recipe.zope2wsgi.egg-info/SOURCES.txt
collective.recipe.zope2wsgi.egg-info/dependency_links.txt
collective.recipe.zope2wsgi.egg-info/entry_points.txt
collective.recipe.zope2wsgi.egg-info/namespace_packages.txt
collective.recipe.zope2wsgi.egg-info/not-zip-safe
collective.recipe.zope2wsgi.egg-info/requires.txt
collective.recipe.zope2wsgi.egg-info/top_level.txt
collective/recipe/__init__.py
collective/recipe/zope2wsgi/README.txt
collective/recipe/zope2wsgi/__init__.py
collective/recipe/zope2wsgi/scripts.py
collective/recipe/zope2wsgi/template.ini
collective/recipe/zope2wsgi/skel/README.txt
collective/recipe/zope2wsgi/skel/Extensions/README.txt
collective/recipe/zope2wsgi/skel/Products/README.txt
collective/recipe/zope2wsgi/skel/bin/runzope.bat.in
collective/recipe/zope2wsgi/skel/bin/runzope.in
collective/recipe/zope2wsgi/skel/bin/zopectl.in
collective/recipe/zope2wsgi/skel/bin/zopeservice.py.in
collective/recipe/zope2wsgi/skel/etc/site.zcml
collective/recipe/zope2wsgi/skel/etc/zope.conf.in
collective/recipe/zope2wsgi/skel/import/Examples.zexp
collective/recipe/zope2wsgi/skel/import/README.txt
collective/recipe/zope2wsgi/skel/import/ZopeTutorialExamples.zexp
collective/recipe/zope2wsgi/skel/lib/python/README.txt.in
collective/recipe/zope2wsgi/skel/log/README.txt
collective/recipe/zope2wsgi/skel/var/README.txt
collective/recipe/zope2wsgi/tests/__init__.py
collective/recipe/zope2wsgi/tests/test_docs.py
collective/recipe/zope2wsgi/utilities/README.txt
collective/recipe/zope2wsgi/utilities/check_catalog.py
collective/recipe/zope2wsgi/utilities/compilezpy.py
collective/recipe/zope2wsgi/utilities/copyzopeskel.py
collective/recipe/zope2wsgi/utilities/decompilezpy.py
collective/recipe/zope2wsgi/utilities/fixheaders.py
collective/recipe/zope2wsgi/utilities/load_site.py
collective/recipe/zope2wsgi/utilities/mkzeoinstance.py
collective/recipe/zope2wsgi/utilities/mkzopeinstance.py
collective/recipe/zope2wsgi/utilities/reindex_catalog.py
collective/recipe/zope2wsgi/utilities/requestprofiler.py
collective/recipe/zope2wsgi/utilities/tracelog.py
collective/recipe/zope2wsgi/utilities/zpasswd.py
collective/recipe/zope2wsgi/utilities/ZODBTools/README.txt
collective/recipe/zope2wsgi/utilities/ZODBTools/__init__.py
