Metadata-Version: 1.0
Name: collective.recipe.zope2wsgi
Version: 0.1
Summary: zc.buildout recipe to generate zope instances using repoze.zope2
Home-page: http://pypi.python.org/pypi/collective.recipe.zope2wsgi
Author: Gael Pasgrimaud
Author-email: gael@gawel.org
License: ZPL
Keywords: wsgi zope2 buildout
Platform: UNKNOWN
Classifier: Framework :: Buildout
Classifier: Intended Audience :: Developers
Classifier: Topic :: Software Development :: Build Tools
Classifier: Topic :: Software Development :: Libraries :: Python Modules
Classifier: License :: OSI Approved :: Zope Public License
Classifier: Development Status :: 4 - Beta
Classifier: Framework :: Zope2
Classifier: Topic :: Internet :: WWW/HTTP :: WSGI
